mathematishia/__init__.py
mathematishia/interpreter/__init__.py
mathematishia/interpreter/interpreter.py
mathematishia/nodes/__init__.py
mathematishia/nodes/algebraic_term.py
mathematishia/nodes/base.py
mathematishia/nodes/binary_operator.py
mathematishia/nodes/function.py
mathematishia/nodes/number.py
mathematishia/nodes/parenthesis.py
mathematishia/nodes/unary_operator.py
mathematishia/parsing/__init__.py
mathematishia/parsing/_parser.py
mathematishia/parsing/latex2ascii.py
mathematishia/parsing/lexer.py
mathematishia/parsing/tokens.py
mathematishia-0.0.3.dist-info/LICENSE
mathematishia-0.0.3.dist-info/METADATA
mathematishia-0.0.3.dist-info/WHEEL
mathematishia-0.0.3.dist-info/top_level.txt
mathematishia-0.0.3.dist-info/RECORD
