Metadata-Version: 2.1
Name: mathematishia
Version: 0.0.3
Summary: A Computer Algebra System, which computes step-by-step solutions to math problems
Author: RezSat (Yehan Wasura)
Author-email: <wasurayehan@gmail.com>
Keywords: python,CAS,computer algebra system,step-by-step,maths,mathematishia,mathsteps
Classifier: Development Status :: 1 - Planning
Classifier: Intended Audience :: Developers
Classifier: Programming Language :: Python :: 3
Classifier: Operating System :: Unix
Classifier: Operating System :: MacOS :: MacOS X
Classifier: Operating System :: Microsoft :: Windows
License-File: LICENSE
Requires-Dist: sympy
